pysemantics/NlpClient.py
pysemantics/__init__.py
pysemantics/__version__.py
pysemantics-1.0.3.dist-info/LICENSE
pysemantics-1.0.3.dist-info/METADATA
pysemantics-1.0.3.dist-info/WHEEL
pysemantics-1.0.3.dist-info/top_level.txt
pysemantics-1.0.3.dist-info/RECORD
