Metadata-Version: 2.1
Name: pysemantics
Version: 1.0.3
Summary: NLP client for python
Home-page: https://github.com/bstoilov/digitalowl-pysemantics
Author: Borislav Stoilov
Author-email: borislav.stoilov@digitalowl.org
License: MIT
Platform: UNKNOWN
Classifier: Development Status :: 4 - Beta
Classifier: License :: OSI Approved :: MIT License
Classifier: Intended Audience :: Developers
Classifier: Natural Language :: English
Classifier: Programming Language :: Python
Classifier: Programming Language :: Python :: 3
Classifier: Programming Language :: Python :: 3.6
Classifier: Programming Language :: Python :: 3.7
Classifier: Programming Language :: Python :: Implementation :: CPython
Requires-Python: >=3.5.0
Requires-Dist: requests
Requires-Dist: sklearn
Requires-Dist: spatial
Requires-Dist: numpy
